{
  "FieldValue": null,
  "Status": {
    "Status": "Pending",
    "Comment": null
  },
  "Stage": {
    "Id": 0,
    "Value": "Assessment"
  },
  "Theme": {
    "Id": 1,
    "Value": "Governance"
  },
  "Subsector": null,
  "Id": 1113,
  "SourceId": "2000945",
  "DocumentRequired": false,
  "Field": {
    "Choices": {
      "1": "Support for project structuring",
      "2": "Support for environmental licensing",
      "3": "Other"
    },
    "Title": "Type of support from PPI",
    "Type": "ChoiceSingle"
  }
}