{
  "FieldValue": {
    "Type": "Text",
    "Value": "Produtos entregues.\nExB manifestou que não quer alternativa de PPP (Lei 11.079) e solicitou revisão dos estudos."
  },
  "Status": {
    "Status": "Approved",
    "Comment": null
  },
  "Stage": {
    "Id": 0,
    "Value": "Assessment"
  },
  "Theme": {
    "Id": 1,
    "Value": "Governance"
  },
  "Subsector": null,
  "Id": 1048,
  "SourceId": "2000726",
  "DocumentRequired": false,
  "Field": {
    "Title": "Project current status",
    "Type": "TextMulti"
  }
}