{
  "ProjectOrganizations": [
    {
      "Id": 206,
      "Value": "SEPPI"
    }
  ],
  "Guid": "21d6e900-f6d0-4984-9856-1ae601d3b0ad",
  "Name": "Eficientiza&#231;ao Energ&#233;tica - Pal&#225;cios do Governo Federal",
  "Description": "A Definir",
  "Sector": {
    "Id": 2,
    "Value": "Energy"
  },
  "SubSector": {
    "Id": 42,
    "Value": "Other Energy"
  },
  "OtherSubsector": {
    "Id": "6b5a8c33-a6dd-4e58-a8c5-a1bca473a688",
    "Value": "Energy efficiency, and other renewable energy"
  },
  "Territories": [
    {
      "Id": 36,
      "Value": "Brazil"
    }
  ],
  "Locations": [
    "Brasília"
  ],
  "TypeOfProject": [
    "New"
  ],
  "IsPPP": true,
  "IsUnsolicited": false,
  "LegalFramework": {
    "SourceUniqueId": "BRA-1",
    "Title": "Federal",
    "LocalResourceKey": "<%Timeline,BRA-LF-1,Title%>"
  },
  "Packages": [
    {
      "LocalResourceKey": null,
      "ID": 1,
      "Title": "",
      "ContractualArrangements": [
        {
          "SourceUniqueId": "BRA-2",
          "Title": "PPP: Law 11.079/04",
          "LocalResourceKey": "<%Timeline,BRA-CA-2,Title%>"
        }
      ],
      "TenderProcess": null,
      "OtherContractualArrangement": null,
      "OtherTenderProcess": null
    }
  ],
  "TechnicalSupport": {
    "SourceUniqueId": "BRA-1",
    "Title": "FEP",
    "LocalResourceKey": "<%Timeline,BRA-TS-1,Title%>"
  },
  "Threshold": {
    "SourceUniqueId": "BRA-1",
    "Title": "Qualification by Project",
    "LocalResourceKey": "<%Timeline,BRA-TH-1,Title%>"
  },
  "OwnerOrganisation": {
    "Id": 206,
    "Value": "SEPPI"
  },
  "CurrentProjectStatus": {
    "Id": 2,
    "Value": "Project Definition"
  },
  "CurrentProjectStatusCustom": {
    "Id": 1,
    "Value": "Definition"
  },
  "Completion": 0.0,
  "Created": "2025-06-23T16:42:32Z",
  "Modified": "2026-01-22T13:00:27Z",
  "ProjectEstimatedDueDate": "2025-06-23T16:42:31Z",
  "EstimatedCapitalCost": 0.181123,
  "OriginalCurrency": {
    "Id": 27,
    "Value": "BRL"
  },
  "OriginalCurrencyEstimatedCapitalCost": 1.0,
  "ProjectProperties": {
    "Reference": null,
    "IsTimelineDefined": true,
    "LanguagesTimeline": [
      {
        "Code": "en",
        "Title": "English"
      },
      {
        "Code": "por",
        "Title": "Português"
      }
    ]
  },
  "PMLeaderEmail": "adminppi.source@presidencia.gov.br",
  "PMLeaderFirstName": "Adminppi",
  "PMLeaderLastName": "Source",
  "PMLeaderOrganisation": "SEPPI",
  "PMLeaderTelephone": "(empty)",
  "GPSCoordinates": [
    {
      "address": "Brasília, Federal District",
      "location": {
        "x": "-47.9257379",
        "y": "-15.7793842"
      },
      "score": 100.0,
      "attributes": {
        "ResultID": 1,
        "Place_addr": "Brasília, Federal District",
        "City": "Brasília",
        "Subregion": "",
        "Region": "Federal District"
      }
    }
  ]
}