{
  "ProjectOrganizations": [
    {
      "Id": 206,
      "Value": "SEPPI"
    }
  ],
  "Guid": "bf3ca782-808c-4976-8571-669b139f6eb2",
  "Name": "Floresta Nacional de Ipanema/SP",
  "Description": "A Definir",
  "Sector": {
    "Id": 7,
    "Value": "Other"
  },
  "SubSector": {
    "Id": 41,
    "Value": "Other"
  },
  "OtherSubsector": {
    "Id": "05b92bc8-a5f7-4601-91aa-ccd89039dfac",
    "Value": "Parques e Florestas para visitação"
  },
  "Territories": [
    {
      "Id": 36,
      "Value": "Brazil"
    }
  ],
  "Locations": [
    "São Paulo"
  ],
  "TypeOfProject": [
    "Refurbishment/Replacement"
  ],
  "IsPPP": true,
  "IsUnsolicited": false,
  "LegalFramework": {
    "SourceUniqueId": "BRA-1",
    "Title": "Federal",
    "LocalResourceKey": "<%Timeline,BRA-LF-1,Title%>"
  },
  "Packages": [
    {
      "LocalResourceKey": null,
      "ID": 1,
      "Title": null,
      "ContractualArrangements": [
        {
          "SourceUniqueId": "BRA-1",
          "Title": "Concession: Law 8.987/95",
          "LocalResourceKey": "<%Timeline,BRA-CA-1,Title%>"
        }
      ],
      "TenderProcess": {
        "SourceUniqueId": "BRA-1",
        "Title": "Competition",
        "LocalResourceKey": "<%Timeline,BRA-TP-1,Title%>"
      },
      "OtherContractualArrangement": null,
      "OtherTenderProcess": null
    }
  ],
  "TechnicalSupport": {
    "SourceUniqueId": "BRA-2",
    "Title": "BNDES",
    "LocalResourceKey": "<%Timeline,BRA-TS-2,Title%>"
  },
  "Threshold": {
    "SourceUniqueId": "BRA-1",
    "Title": "Qualification by Project",
    "LocalResourceKey": "<%Timeline,BRA-TH-1,Title%>"
  },
  "OwnerOrganisation": {
    "Id": 206,
    "Value": "SEPPI"
  },
  "CurrentProjectStatus": {
    "Id": 2,
    "Value": "Project Definition"
  },
  "CurrentProjectStatusCustom": {
    "Id": 1,
    "Value": "Definition"
  },
  "Completion": 0.01,
  "Created": "2025-03-18T23:30:38Z",
  "Modified": "2025-10-08T16:41:02Z",
  "ProjectEstimatedDueDate": "2025-03-18T23:30:38Z",
  "EstimatedCapitalCost": 1161600.0,
  "OriginalCurrency": {
    "Id": 27,
    "Value": "BRL"
  },
  "OriginalCurrencyEstimatedCapitalCost": 6600000.0,
  "ProjectProperties": {
    "Reference": null,
    "IsTimelineDefined": true,
    "LanguagesTimeline": [
      {
        "Code": "en",
        "Title": "English"
      },
      {
        "Code": "por",
        "Title": "Português"
      }
    ]
  },
  "PMLeaderEmail": "adminppi.source@presidencia.gov.br",
  "PMLeaderFirstName": "Adminppi",
  "PMLeaderLastName": "Source",
  "GPSCoordinates": [
    {
      "address": "Sao Paulo",
      "location": {
        "x": "-46.6382522",
        "y": "-23.5486657"
      },
      "score": 100.0,
      "attributes": {
        "ResultID": 1,
        "Place_addr": "Sao Paulo",
        "City": "Sao Paulo",
        "Subregion": "",
        "Region": "Sao Paulo"
      }
    }
  ]
}